__builtins__.pyi
_boot.pyi
_boot_fat.pyi
_onewire.pyi
_thread.pyi
binascii.pyi
cmath.pyi
cryptolib.pyi
deflate.pyi
dht.pyi
ds18x20.pyi
errno.pyi
framebuf.pyi
gc.pyi
hashlib.pyi
heapq.pyi
machine.pyi
math.pyi
micropython.pyi
neopixel.pyi
onewire.pyi
platform.pyi
random.pyi
rp2/__init__.pyi
rp2/asm_pio.pyi
select.pyi
time.pyi
uarray.pyi
uasyncio.pyi
ubinascii.pyi
ubluetooth.pyi
ucollections.pyi
ucryptolib.pyi
uctypes.pyi
uerrno.pyi
uhashlib.pyi
uheapq.pyi
uio.pyi
ujson.pyi
umachine.pyi
uos.pyi
uplatform.pyi
urandom.pyi
ure.pyi
uselect.pyi
usocket.pyi
ussl.pyi
ustruct.pyi
usys.pyi
utime.pyi
uwebsocket.pyi
uzlib.pyi
vfs.pyi
micropython_rp2_rpi_pico_stubs-1.27.0.post1.dist-info/LICENSE.md
micropython_rp2_rpi_pico_stubs-1.27.0.post1.dist-info/METADATA
micropython_rp2_rpi_pico_stubs-1.27.0.post1.dist-info/WHEEL
micropython_rp2_rpi_pico_stubs-1.27.0.post1.dist-info/RECORD
