Metadata-Version: 2.3
Name: micropython-rp2-rpi_pico-stubs
Version: 1.27.0.post1
Summary: MicroPython stubs
License: MIT
Author: Jos Verlinde
Author-email: josverl@users.noreply.github.com
Classifier: Typing :: Stubs Only
Classifier: Development Status :: 5 - Production/Stable
Classifier: Programming Language :: Python
Classifier: Programming Language :: Python :: 3
Classifier: Programming Language :: Python :: 3 :: Only
Classifier: Programming Language :: Python :: Implementation :: MicroPython
Classifier: Operating System :: OS Independent
Classifier: Topic :: Text Editors :: Integrated Development Environments (IDE)
Classifier: Topic :: Software Development :: Documentation
Classifier: Topic :: Software Development :: Embedded Systems
Classifier: Topic :: Software Development :: Testing
Classifier: Natural Language :: English
Requires-Dist: micropython-stdlib-stubs (>=1.27.0,<1.28.0)
Project-URL: Documentation, https://micropython-stubs.readthedocs.io/
Project-URL: Homepage, https://github.com/josverl/micropython-stubs#micropython-stubs
Project-URL: Repository, https://github.com/josverl/micropython-stubs
